{
    "StartUp": {
        "next": [
            "Finish",
            "Sub_AtAnnos",
            "Sub_AtStartup",
            "Sub_AtLogin",
            "StartApp"
        ]
    },
    "Sub_AtAnnos": {
        "recognition": "TemplateMatch",
        "template": "StartUp/AnnoX.png",
        "roi": [
            1226,
            52,
            51,
            50
        ],
        "action": "Click",
        "is_sub": true
    },
    "Sub_AtStartup": {
        "recognition": "TemplateMatch",
        "template": "StartUp/StartSleep.png",
        "roi": [
            567,
            508,
            146,
            30
        ],
        "action": "Click",
        "is_sub": true
    },
    "Sub_AtLogin": {
        "recognition": "OCR",
        "expected": "登录",
        "roi": [
            562,
            378,
            156,
            35
        ],
        "action": "Click",
        "is_sub": true
    },
    "Finish": {
        "recognition": "TemplateMatch",
        "template": "StartUp/HomeChat.png",
        "roi": [
            41,
            48,
            31,
            29
        ],
        "action": "StopTask"
    },
    "StartApp": {
        "action": "StartApp",
        "package": "com.tzyz.meng.bilibili/com.snapverse.c1.c1Activity",
        "next": [
            "StartUp"
        ]
    }
}